PACKAGE_LAB_VR_DEMO_SUCCESS/__init__.py
PACKAGE_LAB_VR_DEMO_SUCCESS-99.99.99.dist-info/METADATA
PACKAGE_LAB_VR_DEMO_SUCCESS-99.99.99.dist-info/WHEEL
PACKAGE_LAB_VR_DEMO_SUCCESS-99.99.99.dist-info/top_level.txt
PACKAGE_LAB_VR_DEMO_SUCCESS-99.99.99.dist-info/RECORD
